[{"game":[{"id":1,"players":[{"idPlayer":1,"name":"Dong","rounds":[{"idRound":1,"score":0}]},{"idPlayer":2,"name":"Hoang","rounds":[{"idRound":1,"score":0}]},{"idPlayer":3,"name":"Hieu","rounds":[{"idRound":1,"score":0}]},{"idPlayer":4,"name":"Huy","rounds":[{"idRound":1,"score":0}]}]},{"id":2,"players":[{"idPlayer":1,"name":"Trương bảo hoàng","rounds":[{"idRound":1,"score":4},{"idRound":2,"score":0},{"idRound":3,"score":0},{"idRound":4,"score":0},{"idRound":5,"score":0},{"idRound":6,"score":0}]},{"idPlayer":2,"name":"Hoàng","rounds":[{"idRound":1,"score":3},{"idRound":2,"score":1},{"idRound":3,"score":0},{"idRound":4,"score":0},{"idRound":5,"score":0},{"idRound":6,"score":0}]},{"idPlayer":3,"name":"Đồng","rounds":[{"idRound":1,"score":1},{"idRound":2,"score":1},{"idRound":3,"score":0},{"idRound":4,"score":0},{"idRound":5,"score":0},{"idRound":6,"score":0}]},{"idPlayer":4,"name":"Huy","rounds":[{"idRound":1,"score":9},{"idRound":2,"score":0},{"idRound":3,"score":0},{"idRound":4,"score":0},{"idRound":5,"score":0},{"idRound":6,"score":0}]}]},{"id":3,"players":[{"idPlayer":1,"name":"fasdfsa","rounds":[{"idRound":1,"score":0}]},{"idPlayer":2,"name":"fsaf","rounds":[{"idRound":1,"score":0}]},{"idPlayer":3,"name":"fasfsa","rounds":[{"idRound":1,"score":0}]},{"idPlayer":4,"name":"fsafas","rounds":[{"idRound":1,"score":0}]}]},{"id":4,"players":[{"idPlayer":1,"name":"haha","rounds":[{"idRound":1,"score":10},{"idRound":2,"score":2},{"idRound":3,"score":1},{"idRound":4,"score":8}]},{"idPlayer":2,"name":"haha2","rounds":[{"idRound":1,"score":2},{"idRound":2,"score":0},{"idRound":3,"score":1},{"idRound":4,"score":2}]},{"idPlayer":3,"name":"ahah243","rounds":[{"idRound":1,"score":0},{"idRound":2,"score":0},{"idRound":3,"score":0},{"idRound":4,"score":0}]},{"idPlayer":4,"name":"Đồng ĐỒng","rounds":[{"idRound":1,"score":1},{"idRound":2,"score":0},{"idRound":3,"score":8},{"idRound":4,"score":-3}]}]},{"id":5,"players":[]},{"id":6,"players":[]},{"id":7,"players":[{"idPlayer":1,"name":"đá","rounds":[{"idRound":1,"score":0},{"idRound":2,"score":0},{"idRound":3,"score":0},{"idRound":4,"score":0},{"idRound":5,"score":0},{"idRound":6,"score":0},{"idRound":7,"score":3}]},{"idPlayer":2,"name":"đasa","rounds":[{"idRound":1,"score":1},{"idRound":2,"score":0},{"idRound":3,"score":0},{"idRound":4,"score":0},{"idRound":5,"score":0},{"idRound":6,"score":0},{"idRound":7,"score":0}]},{"idPlayer":3,"name":"đas","rounds":[{"idRound":1,"score":1},{"idRound":2,"score":0},{"idRound":3,"score":0},{"idRound":4,"score":0},{"idRound":5,"score":0},{"idRound":6,"score":0},{"idRound":7,"score":0}]},{"idPlayer":4,"name":"đâsdas","rounds":[{"idRound":1,"score":5},{"idRound":2,"score":0},{"idRound":3,"score":0},{"idRound":4,"score":0},{"idRound":5,"score":0},{"idRound":6,"score":0},{"idRound":7,"score":0}]}]},{"id":8,"players":[]},{"id":9,"players":[]},{"id":10,"players":[{"idPlayer":1,"name":"ádsad","rounds":[{"idRound":1,"score":4}]},{"idPlayer":2,"name":"đâsd","rounds":[{"idRound":1,"score":0}]},{"idPlayer":3,"name":"đá","rounds":[{"idRound":1,"score":5}]},{"idPlayer":4,"name":"ádasd","rounds":[{"idRound":1,"score":0}]}]},{"id":11,"players":[]},{"id":12,"players":[]},{"id":13,"players":[{"idPlayer":1,"name":"ádasd","rounds":[{"idRound":1,"score":6},{"idRound":2,"score":1}]},{"idPlayer":2,"name":"đasa","rounds":[{"idRound":1,"score":1},{"idRound":2,"score":2}]},{"idPlayer":3,"name":"đâs","rounds":[{"idRound":1,"score":1},{"idRound":2,"score":0}]},{"idPlayer":4,"name":"đâs","rounds":[{"idRound":1,"score":0},{"idRound":2,"score":0}]}]},{"id":14,"players":[{"idPlayer":1,"name":"qda","rounds":[{"idRound":1,"score":1},{"idRound":2,"score":3},{"idRound":3,"score":1}]},{"idPlayer":2,"name":"đâsd","rounds":[{"idRound":1,"score":2},{"idRound":2,"score":3},{"idRound":3,"score":1}]}]},{"id":15,"players":[{"idPlayer":1,"name":"đâsda","rounds":[{"idRound":1,"score":3}]}]}]}]